Workbook

Sheet Assumptions
A1: Parameter | B1: Base | C1: Best | D1: Worst
A2: Currency | B2: EUR | C2: EUR | D2: EUR
A3: Start month | B3: 1 | C3: 1 | D3: 1
A4: Time horizon (months) | B4: 24 | C4: 24 | D4: 24
A5: Note: unless stated otherwise, all monetary amounts are in EUR.
A6: Subscription price per user (€/month) | B6: 80 | C6: 80 | D6: 80
A7: Starting customers (month 1) | B7: 20 | C7: 20 | D7: 20
A8: New customers / month (months 1–12) | B8: 10 | C8: 15 | D8: 6
A9: New customers / month (months 13–24) | B9: 15 | C9: 25 | D9: 4
A10: Monthly churn rate (as decimal) | B10: 0.035 | C10: 0.02 | D10: 0.06
A11: Monthly churn rate (as decimal) | B11: 0.035 | C11: 0.02 | D11: 0.06
A12: Gross margin (as decimal) | B12: 0.78 | C12: 0.82 | D12: 0.75
A13: Marketing spend (% of revenue, decimal) | B13: 0.1 | C13: 0.12 | D13: 0.08
A14: Marketing spend (% of revenue, decimal) | B14: 0.1 | C14: 0.12 | D14: 0.08
A15: Salaries (months 1–12) | B15: 15000 | C15: 20000 | D15: 15000
A16: Salaries (months 13–24) | B16: 22000 | C16: 27000 | D16: 25000
A17: Other fixed costs 1–12 | B17: 8000 | C17: 9000 | D17: 8000
... A19: Starting cash balance (€) | B19: 300000 | C19: 300000 | D19: 300000
A20: Notes
A22: Average fully-loaded salary per FTE per month | B22: 6500 | C22: 7000 | D22: 6000
A23: Marketing % roughly aligned with SaaS Capital medians (8% marketing, 13% sales).
A24: Corporate tax rate (on EBIT, decimal) | B24: 0.24 | C24: 0.24 | D24: 0.24
A25: Capex as % of revenue (decimal) | B25: 0.03 | C25: 0.04 | D25: 0.02
A26: Capex as % of revenue (decimal) | B26: 0.03 | C26: 0.04 | D26: 0.02

Sheet P&L_Monthly
A1: Metric | B1: Month 1 | C1: Month 2 | D1: Month 3 | E1: Month 4 | F1: Month 5 | G1: Month 6 | H1: Month 7 | I1: Month 8 | J1: Month 9 | K1: Month 10 | L1: Month 11 | M1: Month 12 | N1: Month 13 | O1: Month 14 | P1: Month 15 | Q1: Month 16 | R1: Month 17 | S1: Month 18 | T1: Month 19 | U1: Month 20 | V1: Month 21 | W1: Month 22 | X1: Month 23 | Y1: Month 24
A3: Customers - Base | B3: ='Assumptions'!$B$7 | C3: =B3*(1-'Assumptions'!$B$10)+IF(COLUMN()-1<=12,'Assumptions'!$B$8,'Assumptions'!$B$9) | D3: =C3*(1-'Assumptions'!$B$10)+IF(COLUMN()-1<=12,'Assumptions'!$B$8,'Assumptions'!$B$9) | E3: =D3*(1-'Assumptions'!$B$10)+IF(COLUMN()-1<=12,'Assumptions'!$B$8,'Assumptions'!$B$9) | F3: =E3*(1-'Assumptions'!$B$10)+IF(COLUMN()-1<=12,'Assumptions'!$B$8,'Assumptions'!$B$9) | G3: =F3*(1-'Assumptions'!$B$10)+IF(COLUMN()-1<=12,'Assumptions'!$B$8,'Assumptions'!$B$9) | H3: =G3*(1-'Assumptions'!$B$10)+IF(COLUMN()-1<=12,'Assumptions'!$B$8,'Assumptions'!$B$9) | I3: =H3*(1-'Assumptions'!$B$10)+IF(COLUMN()-1<=12,'Assumptions'!$B$8,'Assumptions'!$B$9) | J3: =I3*(1-'Assumptions'!$B$10)+IF(COLUMN()-1<=12,'Assumptions'!$B$8,'Assumptions'!$B$9) | ... Y3: =X3*(1-'Assumptions'!$B$10)+IF(COLUMN()-1<=12,'Assumptions'!$B$8,'Assumptions'!$B$9)
A4: Customers - Best | B4: ='Assumptions'!$C$7 | C4: =B4*(1-'Assumptions'!$C$10)+IF(COLUMN()-1<=12,'Assumptions'!$C$8,'Assumptions'!$C$9) | D4: =C4*(1-'Assumptions'!$C$10)+IF(COLUMN()-1<=12,'Assumptions'!$C$8,'Assumptions'!$C$9) | E4: =D4*(1-'Assumptions'!$C$10)+IF(COLUMN()-1<=12,'Assumptions'!$C$8,'Assumptions'!$C$9) | F4: =E4*(1-'Assumptions'!$C$10)+IF(COLUMN()-1<=12,'Assumptions'!$C$8,'Assumptions'!$C$9) | G4: =F4*(1-'Assumptions'!$C$10)+IF(COLUMN()-1<=12,'Assumptions'!$C$8,'Assumptions'!$C$9) | H4: =G4*(1-'Assumptions'!$C$10)+IF(COLUMN()-1<=12,'Assumptions'!$C$8,'Assumptions'!$C$9) | I4: =H4*(1-'Assumptions'!$C$10)+IF(COLUMN()-1<=12,'Assumptions'!$C$8,'Assumptions'!$C$9) | J4: =I4*(1-'Assumptions'!$C$10)+IF(COLUMN()-1<=12,'Assumptions'!$C$8,'Assumptions'!$C$9) | ... Y4: =X4*(1-'Assumptions'!$C$10)+IF(COLUMN()-1<=12,'Assumptions'!$C$8,'Assumptions'!$C$9)
A5: Customers - Worst | B5: ='Assumptions'!$D$7 | C5: =B5*(1-'Assumptions'!$D$10)+IF(COLUMN()-1<=12,'Assumptions'!$D$8,'Assumptions'!$D$9) | D5: =C5*(1-'Assumptions'!$D$10)+IF(COLUMN()-1<=12,'Assumptions'!$D$8,'Assumptions'!$D$9) | E5: =D5*(1-'Assumptions'!$D$10)+IF(COLUMN()-1<=12,'Assumptions'!$D$8,'Assumptions'!$D$9) | F5: =E5*(1-'Assumptions'!$D$10)+IF(COLUMN()-1<=12,'Assumptions'!$D$8,'Assumptions'!$D$9) | G5: =F5*(1-'Assumptions'!$D$10)+IF(COLUMN()-1<=12,'Assumptions'!$D$8,'Assumptions'!$D$9) | H5: =G5*(1-'Assumptions'!$D$10)+IF(COLUMN()-1<=12,'Assumptions'!$D$8,'Assumptions'!$D$9) | I5: =H5*(1-'Assumptions'!$D$10)+IF(COLUMN()-1<=12,'Assumptions'!$D$8,'Assumptions'!$D$9) | J5: =I5*(1-'Assumptions'!$D$10)+IF(COLUMN()-1<=12,'Assumptions'!$D$8,'Assumptions'!$D$9) | ... Y5: =X5*(1-'Assumptions'!$D$10)+IF(COLUMN()-1<=12,'Assumptions'!$D$8,'Assumptions'!$D$9)
A7: Revenue - Base | B7: =B3*'Assumptions'!$B$6 | C7: =C3*'Assumptions'!$B$6 | D7: =D3*'Assumptions'!$B$6 | E7: =E3*'Assumptions'!$B$6 | F7: =F3*'Assumptions'!$B$6 | G7: =G3*'Assumptions'!$B$6 | H7: =H3*'Assumptions'!$B$6 | I7: =I3*'Assumptions'!$B$6 | ... Y7: =Y3*'Assumptions'!$B$6
A8: Revenue - Best | B8: =B4*'Assumptions'!$C$6 | C8: =C4*'Assumptions'!$C$6 | D8: =D4*'Assumptions'!$C$6 | E8: =E4*'Assumptions'!$C$6 | F8: =F4*'Assumptions'!$C$6 | G8: =G4*'Assumptions'!$C$6 | H8: =H4*'Assumptions'!$C$6 | I8: =I4*'Assumptions'!$C$6 | ... Y8: =Y4*'Assumptions'!$C$6
A9: Revenue - Worst | B9: =B5*'Assumptions'!$D$6 | C9: =C5*'Assumptions'!$D$6 | D9: =D5*'Assumptions'!$D$6 | E9: =E5*'Assumptions'!$D$6 | F9: =F5*'Assumptions'!$D$6 | G9: =G5*'Assumptions'!$D$6 | H9: =H5*'Assumptions'!$D$6 | I9: =I5*'Assumptions'!$D$6 | ... Y9: =Y5*'Assumptions'!$D$6
A11: COGS - Base | B11: =B7*(1-'Assumptions'!$B$12) | C11: =C7*(1-'Assumptions'!$B$12) | D11: =D7*(1-'Assumptions'!$B$12) | E11: =E7*(1-'Assumptions'!$B$12) | F11: =F7*(1-'Assumptions'!$B$12) | G11: =G7*(1-'Assumptions'!$B$12) | H11: =H7*(1-'Assumptions'!$B$12) | I11: =I7*(1-'Assumptions'!$B$12) | ... Y11: =Y7*(1-'Assumptions'!$B$12)
A12: COGS - Best | B12: =B8*(1-'Assumptions'!$C$12) | C12: =C8*(1-'Assumptions'!$C$12) | D12: =D8*(1-'Assumptions'!$C$12) | E12: =E8*(1-'Assumptions'!$C$12) | F12: =F8*(1-'Assumptions'!$C$12) | G12: =G8*(1-'Assumptions'!$C$12) | H12: =H8*(1-'Assumptions'!$C$12) | I12: =I8*(1-'Assumptions'!$C$12) | ... Y12: =Y8*(1-'Assumptions'!$C$12)
A13: COGS - Worst | B13: =B9*(1-'Assumptions'!$D$12) | C13: =C9*(1-'Assumptions'!$D$12) | D13: =D9*(1-'Assumptions'!$D$12) | E13: =E9*(1-'Assumptions'!$D$12) | F13: =F9*(1-'Assumptions'!$D$12) | G13: =G9*(1-'Assumptions'!$D$12) | H13: =H9*(1-'Assumptions'!$D$12) | I13: =I9*(1-'Assumptions'!$D$12) | ... Y13: =Y9*(1-'Assumptions'!$D$12)
A15: Gross margin - Base | B15: =B7-B11 | C15: =C7-C11 | D15: =D7-D11 | E15: =E7-E11 | F15: =F7-F11 | G15: =G7-G11 | H15: =H7-H11 | I15: =I7-I11 | ... Y15: =Y7-Y11
A16: Gross margin - Best | B16: =B8-B12 | C16: =C8-C12 | D16: =D8-D12 | E16: =E8-E12 | F16: =F8-F12 | G16: =G8-G12 | H16: =H8-H12 | I16: =I8-I12 | ... Y16: =Y8-Y12
A17: Gross margin - Worst | B17: =B9-B13 | C17: =C9-C13 | D17: =D9-D13 | E17: =E9-E13 | F17: =F9-F13 | G17: =G9-G13 | H17: =H9-H13 | I17: =I9-I13 | ... Y17: =Y9-Y13
A19: Marketing - Base | B19: =B7*'Assumptions'!$B$13 | C19: =C7*'Assumptions'!$B$13 | D19: =D7*'Assumptions'!$B$13 | E19: =E7*'Assumptions'!$B$13 | F19: =F7*'Assumptions'!$B$13 | G19: =G7*'Assumptions'!$B$13 | H19: =H7*'Assumptions'!$B$13 | I19: =I7*'Assumptions'!$B$13 | ... Y19: =Y7*'Assumptions'!$B$13
A20: Marketing - Best | B20: =B8*'Assumptions'!$C$13 | C20: =C8*'Assumptions'!$C$13 | D20: =D8*'Assumptions'!$C$13 | E20: =E8*'Assumptions'!$C$13 | F20: =F8*'Assumptions'!$C$13 | G20: =G8*'Assumptions'!$C$13 | H20: =H8*'Assumptions'!$C$13 | I20: =I8*'Assumptions'!$C$13 | ... Y20: =Y8*'Assumptions'!$C$13
A21: Marketing - Worst | B21: =B9*'Assumptions'!$D$13 | C21: =C9*'Assumptions'!$D$13 | D21: =D9*'Assumptions'!$D$13 | E21: =E9*'Assumptions'!$D$13 | F21: =F9*'Assumptions'!$D$13 | G21: =G9*'Assumptions'!$D$13 | H21: =H9*'Assumptions'!$D$13 | I21: =I9*'Assumptions'!$D$13 | ... Y21: =Y9*'Assumptions'!$D$13
A23: Salaries - Base | B23: =IF(COLUMN()-1<=12,'Assumptions'!$B$15,'Assumptions'!$B$16) | C23: =IF(COLUMN()-1<=12,'Assumptions'!$B$15,'Assumptions'!$B$16) | D23: =IF(COLUMN()-1<=12,'Assumptions'!$B$15,'Assumptions'!$B$16) | E23: =IF(COLUMN()-1<=12,'Assumptions'!$B$15,'Assumptions'!$B$16) | F23: =IF(COLUMN()-1<=12,'Assumptions'!$B$15,'Assumptions'!$B$16) | G23: =IF(COLUMN()-1<=12,'Assumptions'!$B$15,'Assumptions'!$B$16) | H23: =IF(COLUMN()-1<=12,'Assumptions'!$B$15,'Assumptions'!$B$16) | I23: =IF(COLUMN()-1<=12,'Assumptions'!$B$15,'Assumptions'!$B$16) | ... Y23: =IF(COLUMN()-1<=12,'Assumptions'!$B$15,'Assumptions'!$B$16)
A24: Salaries - Best | B24: =IF(COLUMN()-1<=12,'Assumptions'!$C$15,'Assumptions'!$C$16) | C24: =IF(COLUMN()-1<=12,'Assumptions'!$C$15,'Assumptions'!$C$16) | D24: =IF(COLUMN()-1<=12,'Assumptions'!$C$15,'Assumptions'!$C$16) | E24: =IF(COLUMN()-1<=12,'Assumptions'!$C$15,'Assumptions'!$C$16) | F24: =IF(COLUMN()-1<=12,'Assumptions'!$C$15,'Assumptions'!$C$16) | G24: =IF(COLUMN()-1<=12,'Assumptions'!$C$15,'Assumptions'!$C$16) | H24: =IF(COLUMN()-1<=12,'Assumptions'!$C$15,'Assumptions'!$C$16) | I24: =IF(COLUMN()-1<=12,'Assumptions'!$C$15,'Assumptions'!$C$16) | ... Y24: =IF(COLUMN()-1<=12,'Assumptions'!$C$15,'Assumptions'!$C$16)
A25: Salaries - Worst | B25: =IF(COLUMN()-1<=12,'Assumptions'!$D$15,'Assumptions'!$D$16) | C25: =IF(COLUMN()-1<=12,'Assumptions'!$D$15,'Assumptions'!$D$16) | D25: =IF(COLUMN()-1<=12,'Assumptions'!$D$15,'Assumptions'!$D$16) | E25: =IF(COLUMN()-1<=12,'Assumptions'!$D$15,'Assumptions'!$D$16) | F25: =IF(COLUMN()-1<=12,'Assumptions'!$D$15,'Assumptions'!$D$16) | G25: =IF(COLUMN()-1<=12,'Assumptions'!$D$15,'Assumptions'!$D$16) | H25: =IF(COLUMN()-1<=12,'Assumptions'!$D$15,'Assumptions'!$D$16) | I25: =IF(COLUMN()-1<=12,'Assumptions'!$D$15,'Assumptions'!$D$16) | ... Y25: =IF(COLUMN()-1<=12,'Assumptions'!$D$15,'Assumptions'!$D$16)
A27: Other fixed - Base | B27: =IF(COLUMN()-1<=12,'Assumptions'!$B$17,'Assumptions'!$B$18) | C27: =IF(COLUMN()-1<=12,'Assumptions'!$B$17,'Assumptions'!$B$18) | D27: =IF(COLUMN()-1<=12,'Assumptions'!$B$17,'Assumptions'!$B$18) | E27: =IF(COLUMN()-1<=12,'Assumptions'!$B$17,'Assumptions'!$B$18) | F27: =IF(COLUMN()-1<=12,'Assumptions'!$B$17,'Assumptions'!$B$18) | G27: =IF(COLUMN()-1<=12,'Assumptions'!$B$17,'Assumptions'!$B$18) | H27: =IF(COLUMN()-1<=12,'Assumptions'!$B$17,'Assumptions'!$B$18) | I27: =IF(COLUMN()-1<=12,'Assumptions'!$B$17,'Assumptions'!$B$18) | ... Y27: =IF(COLUMN()-1<=12,'Assumptions'!$B$17,'Assumptions'!$B$18)
A28: Other fixed - Best | B28: =IF(COLUMN()-1<=12,'Assumptions'!$C$17,'Assumptions'!$C$18) | C28: =IF(COLUMN()-1<=12,'Assumptions'!$C$17,'Assumptions'!$C$18) | D28: =IF(COLUMN()-1<=12,'Assumptions'!$C$17,'Assumptions'!$C$18) | E28: =IF(COLUMN()-1<=12,'Assumptions'!$C$17,'Assumptions'!$C$18) | F28: =IF(COLUMN()-1<=12,'Assumptions'!$C$17,'Assumptions'!$C$18) | G28: =IF(COLUMN()-1<=12,'Assumptions'!$C$17,'Assumptions'!$C$18) | H28: =IF(COLUMN()-1<=12,'Assumptions'!$C$17,'Assumptions'!$C$18) | I28: =IF(COLUMN()-1<=12,'Assumptions'!$C$17,'Assumptions'!$C$18) | ... Y28: =IF(COLUMN()-1<=12,'Assumptions'!$C$17,'Assumptions'!$C$18)
A29: Other fixed - Worst | B29: =IF(COLUMN()-1<=12,'Assumptions'!$D$17,'Assumptions'!$D$18) | C29: =IF(COLUMN()-1<=12,'Assumptions'!$D$17,'Assumptions'!$D$18) | D29: =IF(COLUMN()-1<=12,'Assumptions'!$D$17,'Assumptions'!$D$18) | E29: =IF(COLUMN()-1<=12,'Assumptions'!$D$17,'Assumptions'!$D$18) | F29: =IF(COLUMN()-1<=12,'Assumptions'!$D$17,'Assumptions'!$D$18) | G29: =IF(COLUMN()-1<=12,'Assumptions'!$D$17,'Assumptions'!$D$18) | H29: =IF(COLUMN()-1<=12,'Assumptions'!$D$17,'Assumptions'!$D$18) | I29: =IF(COLUMN()-1<=12,'Assumptions'!$D$17,'Assumptions'!$D$18) | ... Y29: =IF(COLUMN()-1<=12,'Assumptions'!$D$17,'Assumptions'!$D$18)
A31: EBITDA - Base | B31: =B15-B19-B23-B27 | C31: =C15-C19-C23-C27 | D31: =D15-D19-D23-D27 | E31: =E15-E19-E23-E27 | F31: =F15-F19-F23-F27 | G31: =G15-G19-G23-G27 | H31: =H15-H19-H23-H27 | I31: =I15-I19-I23-I27 | ... Y31: =Y15-Y19-Y23-Y27
A32: EBITDA - Best | B32: =B16-B20-B24-B28 | C32: =C16-C20-C24-C28 | D32: =D16-D20-D24-D28 | E32: =E16-E20-E24-E28 | F32: =F16-F20-F24-F28 | G32: =G16-G20-G24-G28 | H32: =H16-H20-H24-H28 | I32: =I16-I20-I24-I28 | ... Y32: =Y16-Y20-Y24-Y28
A33: EBITDA - Worst | B33: =B17-B21-B25-B29 | C33: =C17-C21-C25-C29 | D33: =D17-D21-D25-D29 | E33: =E17-E21-E25-E29 | F33: =F17-F21-F25-F29 | G33: =G17-G21-G25-G29 | H33: =H17-H21-H25-H29 | I33: =I17-I21-I25-I29 | ... Y33: =Y17-Y21-Y25-Y29
A35: Capex - Base | B35: =B7*'Assumptions'!$B$25 | C35: =C7*'Assumptions'!$B$25 | D35: =D7*'Assumptions'!$B$25 | E35: =E7*'Assumptions'!$B$25 | F35: =F7*'Assumptions'!$B$25 | G35: =G7*'Assumptions'!$B$25 | H35: =H7*'Assumptions'!$B$25 | I35: =I7*'Assumptions'!$B$25 | ... Y35: =Y7*'Assumptions'!$B$25
A36: Capex - Best | B36: =B8*'Assumptions'!$C$25 | C36: =C8*'Assumptions'!$C$25 | D36: =D8*'Assumptions'!$C$25 | E36: =E8*'Assumptions'!$C$25 | F36: =F8*'Assumptions'!$C$25 | G36: =G8*'Assumptions'!$C$25 | H36: =H8*'Assumptions'!$C$25 | I36: =I8*'Assumptions'!$C$25 | ... Y36: =Y8*'Assumptions'!$C$25
A37: Capex - Worst | B37: =B9*'Assumptions'!$D$25 | C37: =C9*'Assumptions'!$D$25 | D37: =D9*'Assumptions'!$D$25 | E37: =E9*'Assumptions'!$D$25 | F37: =F9*'Assumptions'!$D$25 | G37: =G9*'Assumptions'!$D$25 | H37: =H9*'Assumptions'!$D$25 | I37: =I9*'Assumptions'!$D$25 | ... Y37: =Y9*'Assumptions'!$D$25
A38: EBIT - Base | B38: =B31-B34 | C38: =C31-C34 | D38: =D31-D34 | E38: =E31-E34 | F38: =F31-F34 | G38: =G31-G34 | H38: =H31-H34 | I38: =I31-I34 | ... Y38: =Y31-Y34
A39: EBIT - Best | B39: =B32-B35 | C39: =C32-C35 | D39: =D32-D35 | E39: =E32-E35 | F39: =F32-F35 | G39: =G32-G35 | H39: =H32-H35 | I39: =I32-I35 | ... Y39: =Y32-Y35
A40: EBIT - Worst | B40: =B33-B36 | C40: =C33-C36 | D40: =D33-D36 | E40: =E33-E36 | F40: =F33-F36 | G40: =G33-G36 | H40: =H33-H36 | I40: =I33-I36 | ... Y40: =Y33-Y36
A41: Tax - Base | B41: =IF(B37>0,B37*'Assumptions'!$B$24,0) | C41: =IF(C37>0,C37*'Assumptions'!$B$24,0) | D41: =IF(D37>0,D37*'Assumptions'!$B$24,0) | E41: =IF(E37>0,E37*'Assumptions'!$B$24,0) | F41: =IF(F37>0,F37*'Assumptions'!$B$24,0) | G41: =IF(G37>0,G37*'Assumptions'!$B$24,0) | H41: =IF(H37>0,H37*'Assumptions'!$B$24,0) | I41: =IF(I37>0,I37*'Assumptions'!$B$24,0) | ... Y41: =IF(Y37>0,Y37*'Assumptions'!$B$24,0)
A42: Tax - Best | B42: =IF(B38>0,B38*'Assumptions'!$C$24,0) | C42: =IF(C38>0,C38*'Assumptions'!$C$24,0) | D42: =IF(D38>0,D38*'Assumptions'!$C$24,0) | E42: =IF(E38>0,E38*'Assumptions'!$C$24,0) | F42: =IF(F38>0,F38*'Assumptions'!$C$24,0) | G42: =IF(G38>0,G38*'Assumptions'!$C$24,0) | H42: =IF(H38>0,H38*'Assumptions'!$C$24,0) | I42: =IF(I38>0,I38*'Assumptions'!$C$24,0) | ... Y42: =IF(Y38>0,Y38*'Assumptions'!$C$24,0)
A43: Tax - Worst | B43: =IF(B39>0,B39*'Assumptions'!$D$24,0) | C43: =IF(C39>0,C39*'Assumptions'!$D$24,0) | D43: =IF(D39>0,D39*'Assumptions'!$D$24,0) | E43: =IF(E39>0,E39*'Assumptions'!$D$24,0) | F43: =IF(F39>0,F39*'Assumptions'!$D$24,0) | G43: =IF(G39>0,G39*'Assumptions'!$D$24,0) | H43: =IF(H39>0,H39*'Assumptions'!$D$24,0) | I43: =IF(I39>0,I39*'Assumptions'!$D$24,0) | ... Y43: =IF(Y39>0,Y39*'Assumptions'!$D$24,0)
A44: Net income - Base | B44: =B37-B40 | C44: =C37-C40 | D44: =D37-D40 | E44: =E37-E40 | F44: =F37-F40 | G44: =G37-G40 | H44: =H37-H40 | I44: =I37-I40 | ... Y44: =Y37-Y40
A45: Net income - Best | B45: =B38-B41 | C45: =C38-C41 | D45: =D38-D41 | E45: =E38-E41 | F45: =F38-F41 | G45: =G38-G41 | H45: =H38-H41 | I45: =I38-I41 | ... Y45: =Y38-Y41
A46: Net income - Worst | B46: =B39-B42 | C46: =C39-C42 | D46: =D39-D42 | E46: =E39-E42 | F46: =F39-F42 | G46: =G39-G42 | H46: =H39-H42 | I46: =I39-I42 | ... Y46: =Y39-Y42

Sheet Cash_Runway
A1: Metric | B1: Month 1 | C1: Month 2 | D1: Month 3 | E1: Month 4 | F1: Month 5 | G1: Month 6 | H1: Month 7 | I1: Month 8 | J1: Month 9 | K1: Month 10 | L1: Month 11 | M1: Month 12 | N1: Month 13 | O1: Month 14 | P1: Month 15 | Q1: Month 16 | R1: Month 17 | S1: Month 18 | T1: Month 19 | U1: Month 20 | V1: Month 21 | W1: Month 22 | X1: Month 23 | Y1: Month 24
A3: Opening cash - Base | B3: ='Assumptions'!$B$19 | C3: =B5 | D3: =C5 | E3: =D5 | F3: =E5 | G3: =F5 | H3: =G5 | I3: =H5 | J3: =I5 | ... Y3: =X5
A4: Net cash flow (EBITDA) - Base | B4: ='P&L_Monthly'!B31 | C4: ='P&L_Monthly'!C31 | D4: ='P&L_Monthly'!D31 | E4: ='P&L_Monthly'!E31 | F4: ='P&L_Monthly'!F31 | G4: ='P&L_Monthly'!G31 | H4: ='P&L_Monthly'!H31 | I4: ='P&L_Monthly'!I31 | ... Y4: ='P&L_Monthly'!Y31
A5: Closing cash - Base | B5: =B3+B4 | C5: =C3+C4 | D5: =D3+D4 | E5: =E3+E4 | F5: =F3+F4 | G5: =G3+G4 | H5: =H3+H4 | I5: =I3+I4 | ... Y5: =Y3+Y4
A7: Opening cash - Best | B7: ='Assumptions'!$C$19 | C7: =B9 | D7: =C9 | E7: =D9 | F7: =E9 | G7: =F9 | H7: =G9 | I7: =H9 | J7: =I9 | ... Y7: =X9
A8: Net cash flow (EBITDA) - Best | B8: ='P&L_Monthly'!B32 | C8: ='P&L_Monthly'!C32 | D8: ='P&L_Monthly'!D32 | E8: ='P&L_Monthly'!E32 | F8: ='P&L_Monthly'!F32 | G8: ='P&L_Monthly'!G32 | H8: ='P&L_Monthly'!H32 | I8: ='P&L_Monthly'!I32 | ... Y8: ='P&L_Monthly'!Y32
A9: Closing cash - Best | B9: =B7+B8 | C9: =C7+C8 | D9: =D7+D8 | E9: =E7+E8 | F9: =F7+F8 | G9: =G7+G8 | H9: =H7+H8 | I9: =I7+I8 | ... Y9: =Y7+Y8
A11: Opening cash - Worst | B11: ='Assumptions'!$D$19 | C11: =B13 | D11: =C13 | E11: =D13 | F11: =E13 | G11: =F13 | H11: =G13 | I11: =H13 | J11: =I13 | ... Y11: =X13
A12: Net cash flow (EBITDA) - Worst | B12: ='P&L_Monthly'!B33 | C12: ='P&L_Monthly'!C33 | D12: ='P&L_Monthly'!D33 | E12: ='P&L_Monthly'!E33 | F12: ='P&L_Monthly'!F33 | G12: ='P&L_Monthly'!G33 | H12: ='P&L_Monthly'!H33 | I12: ='P&L_Monthly'!I33 | ... Y12: ='P&L_Monthly'!Y33
A13: Closing cash - Worst | B13: =B11+B12 | C13: =C11+C12 | D13: =D11+D12 | E13: =E11+E12 | F13: =F11+F12 | G13: =G11+G12 | H13: =H11+H12 | I13: =I11+I12 | ... Y13: =Y11+Y12
A16: Runway (months) - Base | B16: =COUNTIF(B5:Y5,">0")
A17: Runway (months) - Best | B17: =COUNTIF(B9:Y9,">0")
A18: Runway (months) - Worst | B18: =COUNTIF(B13:Y13,">0")
A20: Net income-based cash flow - Base | B20: ='P&L_Monthly'!B43 | C20: ='P&L_Monthly'!C43 | D20: ='P&L_Monthly'!D43 | E20: ='P&L_Monthly'!E43 | F20: ='P&L_Monthly'!F43 | G20: ='P&L_Monthly'!G43 | H20: ='P&L_Monthly'!H43 | I20: ='P&L_Monthly'!I43 | ... Y20: ='P&L_Monthly'!Y43
A21: Net income-based cash flow - Best | B21: ='P&L_Monthly'!B44 | C21: ='P&L_Monthly'!C44 | D21: ='P&L_Monthly'!D44 | E21: ='P&L_Monthly'!E44 | F21: ='P&L_Monthly'!F44 | G21: ='P&L_Monthly'!G44 | H21: ='P&L_Monthly'!H44 | I21: ='P&L_Monthly'!I44 | ... Y21: ='P&L_Monthly'!Y44
A22: Net income-based cash flow - Worst | B22: ='P&L_Monthly'!B45 | C22: ='P&L_Monthly'!C45 | D22: ='P&L_Monthly'!D45 | E22: ='P&L_Monthly'!E45 | F22: ='P&L_Monthly'!F45 | G22: ='P&L_Monthly'!G45 | H22: ='P&L_Monthly'!H45 | I22: ='P&L_Monthly'!I45 | ... Y22: ='P&L_Monthly'!Y45

Sheet Scenarios
A1: Metric | B1: Base | C1: Best | D1: Worst
A2: Avg monthly burn (€) | B2: =-AVERAGE('P&L_Monthly'!B31:Y31) | C2: =-AVERAGE('P&L_Monthly'!B32:Y32) | D2: =-AVERAGE('P&L_Monthly'!B33:Y33)
A3: Runway (months) | B3: ='Cash_Runway'!B16 | C3: ='Cash_Runway'!B17 | D3: ='Cash_Runway'!B18
A4: Revenue month 24 (€) | B4: ='P&L_Monthly'!Y7 | C4: ='P&L_Monthly'!Y8 | D4: ='P&L_Monthly'!Y9
A5: Peak negative cash (€) | B5: =MIN('Cash_Runway'!B5:Y5) | C5: =MIN('Cash_Runway'!B9:Y9) | D5: =MIN('Cash_Runway'!B13:Y13)

Sheet SaaS_Unit_Econ
A1: Metric | B1: Base | C1: Best | D1: Worst
A2: Total marketing spend 24m (€) | B2: =SUM('P&L_Monthly'!B19:Y19) | C2: =SUM('P&L_Monthly'!B20:Y20) | D2: =SUM('P&L_Monthly'!B21:Y21)
A3: Total new customers 24m | B3: =12*'Assumptions'!B8+12*'Assumptions'!B9 | C3: =12*'Assumptions'!C8+12*'Assumptions'!C9 | D3: =12*'Assumptions'!D8+12*'Assumptions'!D9
A4: CAC (€/customer) | B4: =B2/B3 | C4: =C2/C3 | D4: =D2/D3
A5: LTV (€/customer, GM basis) | B5: ='Assumptions'!B6*'Assumptions'!B12/'Assumptions'!B10 | C5: ='Assumptions'!C6*'Assumptions'!C12/'Assumptions'!C10 | D5: ='Assumptions'!D6*'Assumptions'!D12/'Assumptions'!D10
A6: LTV / CAC | B6: =B5/B4 | C6: =C5/C4 | D6: =D5/D4
A7: CAC payback (months, GM basis) | B7: =B4/('Assumptions'!B6*'Assumptions'!B12) | C7: =C4/('Assumptions'!C6*'Assumptions'!C12) | D7: =D4/('Assumptions'!D6*'Assumptions'!D12)
A8: Monthly NRR (no expansion) | B8: =1-'Assumptions'!B10 | C8: =1-'Assumptions'!C10 | D8: =1-'Assumptions'!D10
A9: Annual NRR (no expansion) | B9: =(1-'Assumptions'!B10)^12 | C9: =(1-'Assumptions'!C10)^12 | D9: =(1-'Assumptions'!D10)^12

Sheet Headcount_ARR_per_FTE
A1: Month | B1: Base FTEs | C1: Best FTEs | D1: Worst FTEs | E1: Base ARR run-rate (€) | F1: Best ARR run-rate (€) | G1: Worst ARR run-rate (€) | H1: Base ARR per FTE (€) | I1: Best ARR per FTE (€) | J1: Worst ARR per FTE (€)
A2: 1 | B2: ='P&L_Monthly'!B23/'Assumptions'!B22 | C2: ='P&L_Monthly'!B24/'Assumptions'!C22 | D2: ='P&L_Monthly'!B25/'Assumptions'!D22 | E2: =12*'P&L_Monthly'!B7 | F2: =12*'P&L_Monthly'!B8 | G2: =12*'P&L_Monthly'!B9 | H2: =IF(B2>0,E2/B2,0) | I2: =IF(C2>0,F2/C2,0) | J2: =IF(D2>0,G2/D2,0)
A3: 2 | B3: ='P&L_Monthly'!C23/'Assumptions'!B22 | C3: ='P&L_Monthly'!C24/'Assumptions'!C22 | D3: ='P&L_Monthly'!C25/'Assumptions'!D22 | E3: =12*'P&L_Monthly'!C7 | F3: =12*'P&L_Monthly'!C8 | G3: =12*'P&L_Monthly'!C9 | H3: =IF(B3>0,E3/B3,0) | I3: =IF(C3>0,F3/C3,0) | J3: =IF(D3>0,G3/D3,0)
A4: 3 | B4: ='P&L_Monthly'!D23/'Assumptions'!B22 | C4: ='P&L_Monthly'!D24/'Assumptions'!C22 | D4: ='P&L_Monthly'!D25/'Assumptions'!D22 | E4: =12*'P&L_Monthly'!D7 | F4: =12*'P&L_Monthly'!D8 | G4: =12*'P&L_Monthly'!D9 | H4: =IF(B4>0,E4/B4,0) | I4: =IF(C4>0,F4/C4,0) | J4: =IF(D4>0,G4/D4,0)
A5: 4 | B5: ='P&L_Monthly'!E23/'Assumptions'!B22 | C5: ='P&L_Monthly'!E24/'Assumptions'!C22 | D5: ='P&L_Monthly'!E25/'Assumptions'!D22 | E5: =12*'P&L_Monthly'!E7 | F5: =12*'P&L_Monthly'!E8 | G5: =12*'P&L_Monthly'!E9 | H5: =IF(B5>0,E5/B5,0) | I5: =IF(C5>0,F5/C5,0) | J5: =IF(D5>0,G5/D5,0)
A6: 5 | B6: ='P&L_Monthly'!F23/'Assumptions'!B22 | C6: ='P&L_Monthly'!F24/'Assumptions'!C22 | D6: ='P&L_Monthly'!F25/'Assumptions'!D22 | E6: =12*'P&L_Monthly'!F7 | F6: =12*'P&L_Monthly'!F8 | G6: =12*'P&L_Monthly'!F9 | H6: =IF(B6>0,E6/B6,0) | I6: =IF(C6>0,F6/C6,0) | J6: =IF(D6>0,G6/D6,0)
A7: 6 | B7: ='P&L_Monthly'!G23/'Assumptions'!B22 | C7: ='P&L_Monthly'!G24/'Assumptions'!C22 | D7: ='P&L_Monthly'!G25/'Assumptions'!D22 | E7: =12*'P&L_Monthly'!G7 | F7: =12*'P&L_Monthly'!G8 | G7: =12*'P&L_Monthly'!G9 | H7: =IF(B7>0,E7/B7,0) | I7: =IF(C7>0,F7/C7,0) | J7: =IF(D7>0,G7/D7,0)
A8: 7 | B8: ='P&L_Monthly'!H23/'Assumptions'!B22 | C8: ='P&L_Monthly'!H24/'Assumptions'!C22 | D8: ='P&L_Monthly'!H25/'Assumptions'!D22 | E8: =12*'P&L_Monthly'!H7 | F8: =12*'P&L_Monthly'!H8 | G8: =12*'P&L_Monthly'!H9 | H8: =IF(B8>0,E8/B8,0) | I8: =IF(C8>0,F8/C8,0) | J8: =IF(D8>0,G8/D8,0)
A9: 8 | B9: ='P&L_Monthly'!I23/'Assumptions'!B22 | C9: ='P&L_Monthly'!I24/'Assumptions'!C22 | D9: ='P&L_Monthly'!I25/'Assumptions'!D22 | E9: =12*'P&L_Monthly'!I7 | F9: =12*'P&L_Monthly'!I8 | G9: =12*'P&L_Monthly'!I9 | H9: =IF(B9>0,E9/B9,0) | I9: =IF(C9>0,F9/C9,0) | J9: =IF(D9>0,G9/D9,0)
A10: 9 | B10: ='P&L_Monthly'!J23/'Assumptions'!B22 | C10: ='P&L_Monthly'!J24/'Assumptions'!C22 | D10: ='P&L_Monthly'!J25/'Assumptions'!D22 | E10: =12*'P&L_Monthly'!J7 | F10: =12*'P&L_Monthly'!J8 | G10: =12*'P&L_Monthly'!J9 | H10: =IF(B10>0,E10/B10,0) | I10: =IF(C10>0,F10/C10,0) | J10: =IF(D10>0,G10/D10,0)
A11: 10 | B11: ='P&L_Monthly'!K23/'Assumptions'!B22 | C11: ='P&L_Monthly'!K24/'Assumptions'!C22 | D11: ='P&L_Monthly'!K25/'Assumptions'!D22 | E11: =12*'P&L_Monthly'!K7 | F11: =12*'P&L_Monthly'!K8 | G11: =12*'P&L_Monthly'!K9 | H11: =IF(B11>0,E11/B11,0) | I11: =IF(C11>0,F11/C11,0) | J11: =IF(D11>0,G11/D11,0)
A12: 11 | B12: ='P&L_Monthly'!L23/'Assumptions'!B22 | C12: ='P&L_Monthly'!L24/'Assumptions'!C22 | D12: ='P&L_Monthly'!L25/'Assumptions'!D22 | E12: =12*'P&L_Monthly'!L7 | F12: =12*'P&L_Monthly'!L8 | G12: =12*'P&L_Monthly'!L9 | H12: =IF(B12>0,E12/B12,0) | I12: =IF(C12>0,F12/C12,0) | J12: =IF(D12>0,G12/D12,0)
A13: 12 | B13: ='P&L_Monthly'!M23/'Assumptions'!B22 | C13: ='P&L_Monthly'!M24/'Assumptions'!C22 | D13: ='P&L_Monthly'!M25/'Assumptions'!D22 | E13: =12*'P&L_Monthly'!M7 | F13: =12*'P&L_Monthly'!M8 | G13: =12*'P&L_Monthly'!M9 | H13: =IF(B13>0,E13/B13,0) | I13: =IF(C13>0,F13/C13,0) | J13: =IF(D13>0,G13/D13,0)
A14: 13 | B14: ='P&L_Monthly'!N23/'Assumptions'!B22 | C14: ='P&L_Monthly'!N24/'Assumptions'!C22 | D14: ='P&L_Monthly'!N25/'Assumptions'!D22 | E14: =12*'P&L_Monthly'!N7 | F14: =12*'P&L_Monthly'!N8 | G14: =12*'P&L_Monthly'!N9 | H14: =IF(B14>0,E14/B14,0) | I14: =IF(C14>0,F14/C14,0) | J14: =IF(D14>0,G14/D14,0)
A15: 14 | B15: ='P&L_Monthly'!O23/'Assumptions'!B22 | C15: ='P&L_Monthly'!O24/'Assumptions'!C22 | D15: ='P&L_Monthly'!O25/'Assumptions'!D22 | E15: =12*'P&L_Monthly'!O7 | F15: =12*'P&L_Monthly'!O8 | G15: =12*'P&L_Monthly'!O9 | H15: =IF(B15>0,E15/B15,0) | I15: =IF(C15>0,F15/C15,0) | J15: =IF(D15>0,G15/D15,0)
A16: 15 | B16: ='P&L_Monthly'!P23/'Assumptions'!B22 | C16: ='P&L_Monthly'!P24/'Assumptions'!C22 | D16: ='P&L_Monthly'!P25/'Assumptions'!D22 | E16: =12*'P&L_Monthly'!P7 | F16: =12*'P&L_Monthly'!P8 | G16: =12*'P&L_Monthly'!P9 | H16: =IF(B16>0,E16/B16,0) | I16: =IF(C16>0,F16/C16,0) | J16: =IF(D16>0,G16/D16,0)
A17: 16 | B17: ='P&L_Monthly'!Q23/'Assumptions'!B22 | C17: ='P&L_Monthly'!Q24/'Assumptions'!C22 | D17: ='P&L_Monthly'!Q25/'Assumptions'!D22 | E17: =12*'P&L_Monthly'!Q7 | F17: =12*'P&L_Monthly'!Q8 | G17: =12*'P&L_Monthly'!Q9 | H17: =IF(B17>0,E17/B17,0) | I17: =IF(C17>0,F17/C17,0) | J17: =IF(D17>0,G17/D17,0)
A18: 17 | B18: ='P&L_Monthly'!R23/'Assumptions'!B22 | C18: ='P&L_Monthly'!R24/'Assumptions'!C22 | D18: ='P&L_Monthly'!R25/'Assumptions'!D22 | E18: =12*'P&L_Monthly'!R7 | F18: =12*'P&L_Monthly'!R8 | G18: =12*'P&L_Monthly'!R9 | H18: =IF(B18>0,E18/B18,0) | I18: =IF(C18>0,F18/C18,0) | J18: =IF(D18>0,G18/D18,0)
A19: 18 | B19: ='P&L_Monthly'!S23/'Assumptions'!B22 | C19: ='P&L_Monthly'!S24/'Assumptions'!C22 | D19: ='P&L_Monthly'!S25/'Assumptions'!D22 | E19: =12*'P&L_Monthly'!S7 | F19: =12*'P&L_Monthly'!S8 | G19: =12*'P&L_Monthly'!S9 | H19: =IF(B19>0,E19/B19,0) | I19: =IF(C19>0,F19/C19,0) | J19: =IF(D19>0,G19/D19,0)
A20: 19 | B20: ='P&L_Monthly'!T23/'Assumptions'!B22 | C20: ='P&L_Monthly'!T24/'Assumptions'!C22 | D20: ='P&L_Monthly'!T25/'Assumptions'!D22 | E20: =12*'P&L_Monthly'!T7 | F20: =12*'P&L_Monthly'!T8 | G20: =12*'P&L_Monthly'!T9 | H20: =IF(B20>0,E20/B20,0) | I20: =IF(C20>0,F20/C20,0) | J20: =IF(D20>0,G20/D20,0)
A21: 20 | B21: ='P&L_Monthly'!U23/'Assumptions'!B22 | C21: ='P&L_Monthly'!U24/'Assumptions'!C22 | D21: ='P&L_Monthly'!U25/'Assumptions'!D22 | E21: =12*'P&L_Monthly'!U7 | F21: =12*'P&L_Monthly'!U8 | G21: =12*'P&L_Monthly'!U9 | H21: =IF(B21>0,E21/B21,0) | I21: =IF(C21>0,F21/C21,0) | J21: =IF(D21>0,G21/D21,0)
A22: 21 | B22: ='P&L_Monthly'!V23/'Assumptions'!B22 | C22: ='P&L_Monthly'!V24/'Assumptions'!C22 | D22: ='P&L_Monthly'!V25/'Assumptions'!D22 | E22: =12*'P&L_Monthly'!V7 | F22: =12*'P&L_Monthly'!V8 | G22: =12*'P&L_Monthly'!V9 | H22: =IF(B22>0,E22/B22,0) | I22: =IF(C22>0,F22/C22,0) | J22: =IF(D22>0,G22/D22,0)
A23: 22 | B23: ='P&L_Monthly'!W23/'Assumptions'!B22 | C23: ='P&L_Monthly'!W24/'Assumptions'!C22 | D23: ='P&L_Monthly'!W25/'Assumptions'!D22 | E23: =12*'P&L_Monthly'!W7 | F23: =12*'P&L_Monthly'!W8 | G23: =12*'P&L_Monthly'!W9 | H23: =IF(B23>0,E23/B23,0) | I23: =IF(C23>0,F23/C23,0) | J23: =IF(D23>0,G23/D23,0)
A24: 23 | B24: ='P&L_Monthly'!X23/'Assumptions'!B22 | C24: ='P&L_Monthly'!X24/'Assumptions'!C22 | D24: ='P&L_Monthly'!X25/'Assumptions'!D22 | E24: =12*'P&L_Monthly'!X7 | F24: =12*'P&L_Monthly'!X8 | G24: =12*'P&L_Monthly'!X9 | H24: =IF(B24>0,E24/B24,0) | I24: =IF(C24>0,F24/C24,0) | J24: =IF(D24>0,G24/D24,0)
A25: 24 | B25: ='P&L_Monthly'!Y23/'Assumptions'!B22 | C25: ='P&L_Monthly'!Y24/'Assumptions'!C22 | D25: ='P&L_Monthly'!Y25/'Assumptions'!D22 | E25: =12*'P&L_Monthly'!Y7 | F25: =12*'P&L_Monthly'!Y8 | G25: =12*'P&L_Monthly'!Y9 | H25: =IF(B25>0,E25/B25,0) | I25: =IF(C25>0,F25/C25,0) | J25: =IF(D25>0,G25/D25,0)
A28: Median ARR per FTE over 24m (Base) | B28: =MEDIAN(H2:H25)
A29: Median ARR per FTE over 24m (Best) | B29: =MEDIAN(I2:I25)
A30: Median ARR per FTE over 24m (Worst) | B30: =MEDIAN(J2:J25)
A32: Benchmark ARR per FTE (early-stage SaaS, rough) | B32: 100000

Sheet Rule_of_40
A1: Rule of 40: combines revenue growth and EBITDA margin to assess whether a SaaS business balances growth and profitability (healthy if >= 40%).
A2: Metric | B2: Base | C2: Best | D2: Worst
A3: Revenue Year 1 (€) | B3: =SUM('P&L_Monthly'!B7:M7) | C3: =SUM('P&L_Monthly'!B8:M8) | D3: =SUM('P&L_Monthly'!B9:M9)
A4: Revenue Year 2 (€) | B4: =SUM('P&L_Monthly'!N7:Y7) | C4: =SUM('P&L_Monthly'!N8:Y8) | D4: =SUM('P&L_Monthly'!N9:Y9)
A5: Revenue growth Year2 vs Year1 | B5: =IF(B3>0,B4/B3-1,0) | C5: =IF(C3>0,C4/C3-1,0) | D5: =IF(D2>0,D3/D2-1,0)
A6: EBITDA margin Year 2 | B6: =IF(B4>0,SUM('P&L_Monthly'!N31:Y31)/B4,0) | C6: =IF(C4>0,SUM('P&L_Monthly'!N32:Y32)/C4,0) | D6: =IF(D3>0,SUM('P&L_Monthly'!N33:Y33)/D3,0)
A7: Rule of 40 (growth + EBITDA margin) | B7: =B5+B6 | C7: =C5+C6 | D7: =D4+D5
A9: Rule-of-40 threshold (healthy if >= 0.40) | B9: 0.4

Sheet Sensitivity_LTV_CAC
A1: Churn x Marketing sensitivity (Base scenario)
A2: Each cell shows LTV/CAC ratio under adjusted churn & marketing (Base only)
A3: Churn multiplier \ Marketing multiplier | B3: 0.5 | C3: 1 | D3: 1.5
A4: 0.5 | B4: =IF('SaaS_Unit_Econ'!$B$6>0,'SaaS_Unit_Econ'!$B$6*(1/$A4)*(1/B$3),0) | C4: =IF('SaaS_Unit_Econ'!$B$6>0,'SaaS_Unit_Econ'!$B$6*(1/$A4)*(1/C$3),0) | D4: =IF('SaaS_Unit_Econ'!$B$6>0,'SaaS_Unit_Econ'!$B$6*(1/$A4)*(1/D$3),0)
A5: 1 | B5: =IF('SaaS_Unit_Econ'!$B$6>0,'SaaS_Unit_Econ'!$B$6*(1/$A5)*(1/B$3),0) | C5: =IF('SaaS_Unit_Econ'!$B$6>0,'SaaS_Unit_Econ'!$B$6*(1/$A5)*(1/C$3),0) | D5: =IF('SaaS_Unit_Econ'!$B$6>0,'SaaS_Unit_Econ'!$B$6*(1/$A5)*(1/D$3),0)
A6: 1.5 | B6: =IF('SaaS_Unit_Econ'!$B$6>0,'SaaS_Unit_Econ'!$B$6*(1/$A6)*(1/B$3),0) | C6: =IF('SaaS_Unit_Econ'!$B$6>0,'SaaS_Unit_Econ'!$B$6*(1/$A6)*(1/C$3),0) | D6: =IF('SaaS_Unit_Econ'!$B$6>0,'SaaS_Unit_Econ'!$B$6*(1/$A6)*(1/D$3),0)

Sheet Cohort_Analysis
A1: Expected active customers per acquisition cohort after 6, 12 and 24 months (Base scenario, using starting cohort size and monthly churn).
A2: Acquisition cohort (month) | B2: Active after 6 months | C2: Active after 12 months | D2: Active after 24 months | E2: Age 4 (months) | F2: Age 5 (months) | G2: Age 6 (months) | H2: Age 7 (months) | I2: Age 8 (months) | J2: Age 9 (months) | K2: Age 10 (months) | L2: Age 11 (months) | M2: Age 12 (months) | N2: Age 13 (months) | O2: Age 14 (months) | P2: Age 15 (months) | Q2: Age 16 (months) | R2: Age 17 (months) | S2: Age 18 (months) | T2: Age 19 (months) | U2: Age 20 (months) | V2: Age 21 (months) | W2: Age 22 (months) | X2: Age 23 (months) | Y2: Age 24 (months)
A3: Month 1 | B3: ='Assumptions'!$B$8*(1-'Assumptions'!$B$10)^6 | C3: ='Assumptions'!$B$8*(1-'Assumptions'!$B$10)^12 | D3: ='Assumptions'!$B$8*(1-'Assumptions'!$B$10)^24 | E3: ='Assumptions'!$B$8*(1-'Assumptions'!$B$10)^3 | F3: ='Assumptions'!$B$8*(1-'Assumptions'!$B$10)^4 | G3: ='Assumptions'!$B$8*(1-'Assumptions'!$B$10)^5 | H3: ='Assumptions'!$B$8*(1-'Assumptions'!$B$10)^6 | I3: ='Assumptions'!$B$8*(1-'Assumptions'!$B$10)^7 | J3: ='Assumptions'!$B$8*(1-'Assumptions'!$B$10)^8 | K3: ='Assumptions'!$B$8*(1-'Assumptions'!$B$10)^9 | L3: ='Assumptions'!$B$8*(1-'Assumptions'!$B$10)^10 | M3: ='Assumptions'!$B$8*(1-'Assumptions'!$B$10)^11 | N3: ='Assumptions'!$B$8*(1-'Assumptions'!$B$10)^12 | O3: ='Assumptions'!$B$8*(1-'Assumptions'!$B$10)^13 | P3: ='Assumptions'!$B$8*(1-'Assumptions'!$B$10)^14 | Q3: ='Assumptions'!$B$8*(1-'Assumptions'!$B$10)^15 | R3: ='Assumptions'!$B$8*(1-'Assumptions'!$B$10)^16 | S3: ='Assumptions'!$B$8*(1-'Assumptions'!$B$10)^17 | T3: ='Assumptions'!$B$8*(1-'Assumptions'!$B$10)^18 | U3: ='Assumptions'!$B$8*(1-'Assumptions'!$B$10)^19 | V3: ='Assumptions'!$B$8*(1-'Assumptions'!$B$10)^20 | W3: ='Assumptions'!$B$8*(1-'Assumptions'!$B$10)^21 | X3: ='Assumptions'!$B$8*(1-'Assumptions'!$B$10)^22 | Y3: ='Assumptions'!$B$8*(1-'Assumptions'!$B$10)^23
A4: Month 2 | B4: ='Assumptions'!$B$8*(1-'Assumptions'!$B$10)^6 | C4: ='Assumptions'!$B$8*(1-'Assumptions'!$B$10)^12 | D4: ='Assumptions'!$B$8*(1-'Assumptions'!$B$10)^24 | E4: ='Assumptions'!$B$8*(1-'Assumptions'!$B$10)^3 | F4: ='Assumptions'!$B$8*(1-'Assumptions'!$B$10)^4 | G4: ='Assumptions'!$B$8*(1-'Assumptions'!$B$10)^5 | H4: ='Assumptions'!$B$8*(1-'Assumptions'!$B$10)^6 | I4: ='Assumptions'!$B$8*(1-'Assumptions'!$B$10)^7 | J4: ='Assumptions'!$B$8*(1-'Assumptions'!$B$10)^8 | K4: ='Assumptions'!$B$8*(1-'Assumptions'!$B$10)^9 | L4: ='Assumptions'!$B$8*(1-'Assumptions'!$B$10)^10 | M4: ='Assumptions'!$B$8*(1-'Assumptions'!$B$10)^11 | N4: ='Assumptions'!$B$8*(1-'Assumptions'!$B$10)^12 | O4: ='Assumptions'!$B$8*(1-'Assumptions'!$B$10)^13 | P4: ='Assumptions'!$B$8*(1-'Assumptions'!$B$10)^14 | Q4: ='Assumptions'!$B$8*(1-'Assumptions'!$B$10)^15 | R4: ='Assumptions'!$B$8*(1-'Assumptions'!$B$10)^16 | S4: ='Assumptions'!$B$8*(1-'Assumptions'!$B$10)^17 | T4: ='Assumptions'!$B$8*(1-'Assumptions'!$B$10)^18 | U4: ='Assumptions'!$B$8*(1-'Assumptions'!$B$10)^19 | V4: ='Assumptions'!$B$8*(1-'Assumptions'!$B$10)^20 | W4: ='Assumptions'!$B$8*(1-'Assumptions'!$B$10)^21 | X4: ='Assumptions'!$B$8*(1-'Assumptions'!$B$10)^22
A5: Month 3 | B5: ='Assumptions'!$B$8*(1-'Assumptions'!$B$10)^6 | C5: ='Assumptions'!$B$8*(1-'Assumptions'!$B$10)^12 | D5: ='Assumptions'!$B$8*(1-'Assumptions'!$B$10)^24 | E5: ='Assumptions'!$B$8*(1-'Assumptions'!$B$10)^3 | F5: ='Assumptions'!$B$8*(1-'Assumptions'!$B$10)^4 | G5: ='Assumptions'!$B$8*(1-'Assumptions'!$B$10)^5 | H5: ='Assumptions'!$B$8*(1-'Assumptions'!$B$10)^6 | I5: ='Assumptions'!$B$8*(1-'Assumptions'!$B$10)^7 | J5: ='Assumptions'!$B$8*(1-'Assumptions'!$B$10)^8 | K5: ='Assumptions'!$B$8*(1-'Assumptions'!$B$10)^9 | L5: ='Assumptions'!$B$8*(1-'Assumptions'!$B$10)^10 | M5: ='Assumptions'!$B$8*(1-'Assumptions'!$B$10)^11 | N5: ='Assumptions'!$B$8*(1-'Assumptions'!$B$10)^12 | O5: ='Assumptions'!$B$8*(1-'Assumptions'!$B$10)^13 | P5: ='Assumptions'!$B$8*(1-'Assumptions'!$B$10)^14 | Q5: ='Assumptions'!$B$8*(1-'Assumptions'!$B$10)^15 | R5: ='Assumptions'!$B$8*(1-'Assumptions'!$B$10)^16 | S5: ='Assumptions'!$B$8*(1-'Assumptions'!$B$10)^17 | T5: ='Assumptions'!$B$8*(1-'Assumptions'!$B$10)^18 | U5: ='Assumptions'!$B$8*(1-'Assumptions'!$B$10)^19 | V5: ='Assumptions'!$B$8*(1-'Assumptions'!$B$10)^20 | W5: ='Assumptions'!$B$8*(1-'Assumptions'!$B$10)^21
A6: Month 4 | B6: ='Assumptions'!$B$8*(1-'Assumptions'!$B$10)^6 | C6: ='Assumptions'!$B$8*(1-'Assumptions'!$B$10)^12 | D6: ='Assumptions'!$B$8*(1-'Assumptions'!$B$10)^24 | E6: ='Assumptions'!$B$8*(1-'Assumptions'!$B$10)^3 | F6: ='Assumptions'!$B$8*(1-'Assumptions'!$B$10)^4 | G6: ='Assumptions'!$B$8*(1-'Assumptions'!$B$10)^5 | H6: ='Assumptions'!$B$8*(1-'Assumptions'!$B$10)^6 | I6: ='Assumptions'!$B$8*(1-'Assumptions'!$B$10)^7 | J6: ='Assumptions'!$B$8*(1-'Assumptions'!$B$10)^8 | K6: ='Assumptions'!$B$8*(1-'Assumptions'!$B$10)^9 | L6: ='Assumptions'!$B$8*(1-'Assumptions'!$B$10)^10 | M6: ='Assumptions'!$B$8*(1-'Assumptions'!$B$10)^11 | N6: ='Assumptions'!$B$8*(1-'Assumptions'!$B$10)^12 | O6: ='Assumptions'!$B$8*(1-'Assumptions'!$B$10)^13 | P6: ='Assumptions'!$B$8*(1-'Assumptions'!$B$10)^14 | Q6: ='Assumptions'!$B$8*(1-'Assumptions'!$B$10)^15 | R6: ='Assumptions'!$B$8*(1-'Assumptions'!$B$10)^16 | S6: ='Assumptions'!$B$8*(1-'Assumptions'!$B$10)^17 | T6: ='Assumptions'!$B$8*(1-'Assumptions'!$B$10)^18 | U6: ='Assumptions'!$B$8*(1-'Assumptions'!$B$10)^19 | V6: ='Assumptions'!$B$8*(1-'Assumptions'!$B$10)^20
A7: Month 5 | B7: ='Assumptions'!$B$8*(1-'Assumptions'!$B$10)^6 | C7: ='Assumptions'!$B$8*(1-'Assumptions'!$B$10)^12 | D7: ='Assumptions'!$B$8*(1-'Assumptions'!$B$10)^24 | E7: ='Assumptions'!$B$8*(1-'Assumptions'!$B$10)^3 | F7: ='Assumptions'!$B$8*(1-'Assumptions'!$B$10)^4 | G7: ='Assumptions'!$B$8*(1-'Assumptions'!$B$10)^5 | H7: ='Assumptions'!$B$8*(1-'Assumptions'!$B$10)^6 | I7: ='Assumptions'!$B$8*(1-'Assumptions'!$B$10)^7 | J7: ='Assumptions'!$B$8*(1-'Assumptions'!$B$10)^8 | K7: ='Assumptions'!$B$8*(1-'Assumptions'!$B$10)^9 | L7: ='Assumptions'!$B$8*(1-'Assumptions'!$B$10)^10 | M7: ='Assumptions'!$B$8*(1-'Assumptions'!$B$10)^11 | N7: ='Assumptions'!$B$8*(1-'Assumptions'!$B$10)^12 | O7: ='Assumptions'!$B$8*(1-'Assumptions'!$B$10)^13 | P7: ='Assumptions'!$B$8*(1-'Assumptions'!$B$10)^14 | Q7: ='Assumptions'!$B$8*(1-'Assumptions'!$B$10)^15 | R7: ='Assumptions'!$B$8*(1-'Assumptions'!$B$10)^16 | S7: ='Assumptions'!$B$8*(1-'Assumptions'!$B$10)^17 | T7: ='Assumptions'!$B$8*(1-'Assumptions'!$B$10)^18 | U7: ='Assumptions'!$B$8*(1-'Assumptions'!$B$10)^19
A8: Month 6 | B8: ='Assumptions'!$B$8*(1-'Assumptions'!$B$10)^6 | C8: ='Assumptions'!$B$8*(1-'Assumptions'!$B$10)^12 | D8: ='Assumptions'!$B$8*(1-'Assumptions'!$B$10)^24 | E8: ='Assumptions'!$B$8*(1-'Assumptions'!$B$10)^3 | F8: ='Assumptions'!$B$8*(1-'Assumptions'!$B$10)^4 | G8: ='Assumptions'!$B$8*(1-'Assumptions'!$B$10)^5 | H8: ='Assumptions'!$B$8*(1-'Assumptions'!$B$10)^6 | I8: ='Assumptions'!$B$8*(1-'Assumptions'!$B$10)^7 | J8: ='Assumptions'!$B$8*(1-'Assumptions'!$B$10)^8 | K8: ='Assumptions'!$B$8*(1-'Assumptions'!$B$10)^9 | L8: ='Assumptions'!$B$8*(1-'Assumptions'!$B$10)^10 | M8: ='Assumptions'!$B$8*(1-'Assumptions'!$B$10)^11 | N8: ='Assumptions'!$B$8*(1-'Assumptions'!$B$10)^12 | O8: ='Assumptions'!$B$8*(1-'Assumptions'!$B$10)^13 | P8: ='Assumptions'!$B$8*(1-'Assumptions'!$B$10)^14 | Q8: ='Assumptions'!$B$8*(1-'Assumptions'!$B$10)^15 | R8: ='Assumptions'!$B$8*(1-'Assumptions'!$B$10)^16 | S8: ='Assumptions'!$B$8*(1-'Assumptions'!$B$10)^17 | T8: ='Assumptions'!$B$8*(1-'Assumptions'!$B$10)^18
A9: Month 7 | B9: ='Assumptions'!$B$8*(1-'Assumptions'!$B$10)^6 | C9: ='Assumptions'!$B$8*(1-'Assumptions'!$B$10)^12 | D9: ='Assumptions'!$B$8*(1-'Assumptions'!$B$10)^24 | E9: ='Assumptions'!$B$8*(1-'Assumptions'!$B$10)^3 | F9: ='Assumptions'!$B$8*(1-'Assumptions'!$B$10)^4 | G9: ='Assumptions'!$B$8*(1-'Assumptions'!$B$10)^5 | H9: ='Assumptions'!$B$8*(1-'Assumptions'!$B$10)^6 | I9: ='Assumptions'!$B$8*(1-'Assumptions'!$B$10)^7 | J9: ='Assumptions'!$B$8*(1-'Assumptions'!$B$10)^8 | K9: ='Assumptions'!$B$8*(1-'Assumptions'!$B$10)^9 | L9: ='Assumptions'!$B$8*(1-'Assumptions'!$B$10)^10 | M9: ='Assumptions'!$B$8*(1-'Assumptions'!$B$10)^11 | N9: ='Assumptions'!$B$8*(1-'Assumptions'!$B$10)^12 | O9: ='Assumptions'!$B$8*(1-'Assumptions'!$B$10)^13 | P9: ='Assumptions'!$B$8*(1-'Assumptions'!$B$10)^14 | Q9: ='Assumptions'!$B$8*(1-'Assumptions'!$B$10)^15 | R9: ='Assumptions'!$B$8*(1-'Assumptions'!$B$10)^16 | S9: ='Assumptions'!$B$8*(1-'Assumptions'!$B$10)^17
A10: Month 8 | B10: ='Assumptions'!$B$8*(1-'Assumptions'!$B$10)^6 | C10: ='Assumptions'!$B$8*(1-'Assumptions'!$B$10)^12 | D10: ='Assumptions'!$B$8*(1-'Assumptions'!$B$10)^24 | E10: ='Assumptions'!$B$8*(1-'Assumptions'!$B$10)^3 | F10: ='Assumptions'!$B$8*(1-'Assumptions'!$B$10)^4 | G10: ='Assumptions'!$B$8*(1-'Assumptions'!$B$10)^5 | H10: ='Assumptions'!$B$8*(1-'Assumptions'!$B$10)^6 | I10: ='Assumptions'!$B$8*(1-'Assumptions'!$B$10)^7 | J10: ='Assumptions'!$B$8*(1-'Assumptions'!$B$10)^8 | K10: ='Assumptions'!$B$8*(1-'Assumptions'!$B$10)^9 | L10: ='Assumptions'!$B$8*(1-'Assumptions'!$B$10)^10 | M10: ='Assumptions'!$B$8*(1-'Assumptions'!$B$10)^11 | N10: ='Assumptions'!$B$8*(1-'Assumptions'!$B$10)^12 | O10: ='Assumptions'!$B$8*(1-'Assumptions'!$B$10)^13 | P10: ='Assumptions'!$B$8*(1-'Assumptions'!$B$10)^14 | Q10: ='Assumptions'!$B$8*(1-'Assumptions'!$B$10)^15 | R10: ='Assumptions'!$B$8*(1-'Assumptions'!$B$10)^16
A11: Month 9 | B11: ='Assumptions'!$B$8*(1-'Assumptions'!$B$10)^6 | C11: ='Assumptions'!$B$8*(1-'Assumptions'!$B$10)^12 | D11: ='Assumptions'!$B$8*(1-'Assumptions'!$B$10)^24 | E11: ='Assumptions'!$B$8*(1-'Assumptions'!$B$10)^3 | F11: ='Assumptions'!$B$8*(1-'Assumptions'!$B$10)^4 | G11: ='Assumptions'!$B$8*(1-'Assumptions'!$B$10)^5 | H11: ='Assumptions'!$B$8*(1-'Assumptions'!$B$10)^6 | I11: ='Assumptions'!$B$8*(1-'Assumptions'!$B$10)^7 | J11: ='Assumptions'!$B$8*(1-'Assumptions'!$B$10)^8 | K11: ='Assumptions'!$B$8*(1-'Assumptions'!$B$10)^9 | L11: ='Assumptions'!$B$8*(1-'Assumptions'!$B$10)^10 | M11: ='Assumptions'!$B$8*(1-'Assumptions'!$B$10)^11 | N11: ='Assumptions'!$B$8*(1-'Assumptions'!$B$10)^12 | O11: ='Assumptions'!$B$8*(1-'Assumptions'!$B$10)^13 | P11: ='Assumptions'!$B$8*(1-'Assumptions'!$B$10)^14 | Q11: ='Assumptions'!$B$8*(1-'Assumptions'!$B$10)^15
A12: Month 10 | B12: ='Assumptions'!$B$8*(1-'Assumptions'!$B$10)^6 | C12: ='Assumptions'!$B$8*(1-'Assumptions'!$B$10)^12 | D12: ='Assumptions'!$B$8*(1-'Assumptions'!$B$10)^24 | E12: ='Assumptions'!$B$8*(1-'Assumptions'!$B$10)^3 | F12: ='Assumptions'!$B$8*(1-'Assumptions'!$B$10)^4 | G12: ='Assumptions'!$B$8*(1-'Assumptions'!$B$10)^5 | H12: ='Assumptions'!$B$8*(1-'Assumptions'!$B$10)^6 | I12: ='Assumptions'!$B$8*(1-'Assumptions'!$B$10)^7 | J12: ='Assumptions'!$B$8*(1-'Assumptions'!$B$10)^8 | K12: ='Assumptions'!$B$8*(1-'Assumptions'!$B$10)^9 | L12: ='Assumptions'!$B$8*(1-'Assumptions'!$B$10)^10 | M12: ='Assumptions'!$B$8*(1-'Assumptions'!$B$10)^11 | N12: ='Assumptions'!$B$8*(1-'Assumptions'!$B$10)^12 | O12: ='Assumptions'!$B$8*(1-'Assumptions'!$B$10)^13 | P12: ='Assumptions'!$B$8*(1-'Assumptions'!$B$10)^14
A13: Month 11 | B13: ='Assumptions'!$B$8*(1-'Assumptions'!$B$10)^6 | C13: ='Assumptions'!$B$8*(1-'Assumptions'!$B$10)^12 | D13: ='Assumptions'!$B$8*(1-'Assumptions'!$B$10)^24 | E13: ='Assumptions'!$B$8*(1-'Assumptions'!$B$10)^3 | F13: ='Assumptions'!$B$8*(1-'Assumptions'!$B$10)^4 | G13: ='Assumptions'!$B$8*(1-'Assumptions'!$B$10)^5 | H13: ='Assumptions'!$B$8*(1-'Assumptions'!$B$10)^6 | I13: ='Assumptions'!$B$8*(1-'Assumptions'!$B$10)^7 | J13: ='Assumptions'!$B$8*(1-'Assumptions'!$B$10)^8 | K13: ='Assumptions'!$B$8*(1-'Assumptions'!$B$10)^9 | L13: ='Assumptions'!$B$8*(1-'Assumptions'!$B$10)^10 | M13: ='Assumptions'!$B$8*(1-'Assumptions'!$B$10)^11 | N13: ='Assumptions'!$B$8*(1-'Assumptions'!$B$10)^12 | O13: ='Assumptions'!$B$8*(1-'Assumptions'!$B$10)^13
A14: Month 12 | B14: ='Assumptions'!$B$8*(1-'Assumptions'!$B$10)^6 | C14: ='Assumptions'!$B$8*(1-'Assumptions'!$B$10)^12 | D14: ='Assumptions'!$B$8*(1-'Assumptions'!$B$10)^24 | E14: ='Assumptions'!$B$8*(1-'Assumptions'!$B$10)^3 | F14: ='Assumptions'!$B$8*(1-'Assumptions'!$B$10)^4 | G14: ='Assumptions'!$B$8*(1-'Assumptions'!$B$10)^5 | H14: ='Assumptions'!$B$8*(1-'Assumptions'!$B$10)^6 | I14: ='Assumptions'!$B$8*(1-'Assumptions'!$B$10)^7 | J14: ='Assumptions'!$B$8*(1-'Assumptions'!$B$10)^8 | K14: ='Assumptions'!$B$8*(1-'Assumptions'!$B$10)^9 | L14: ='Assumptions'!$B$8*(1-'Assumptions'!$B$10)^10 | M14: ='Assumptions'!$B$8*(1-'Assumptions'!$B$10)^11 | N14: ='Assumptions'!$B$8*(1-'Assumptions'!$B$10)^12
A15: Month 13 | B15: ='Assumptions'!$B$8*(1-'Assumptions'!$B$10)^6 | C15: ='Assumptions'!$B$8*(1-'Assumptions'!$B$10)^12 | D15: ='Assumptions'!$B$8*(1-'Assumptions'!$B$10)^24 | E15: ='Assumptions'!$B$9*(1-'Assumptions'!$B$10)^3 | F15: ='Assumptions'!$B$9*(1-'Assumptions'!$B$10)^4 | G15: ='Assumptions'!$B$9*(1-'Assumptions'!$B$10)^5 | H15: ='Assumptions'!$B$9*(1-'Assumptions'!$B$10)^6 | I15: ='Assumptions'!$B$9*(1-'Assumptions'!$B$10)^7 | J15: ='Assumptions'!$B$9*(1-'Assumptions'!$B$10)^8 | K15: ='Assumptions'!$B$9*(1-'Assumptions'!$B$10)^9 | L15: ='Assumptions'!$B$9*(1-'Assumptions'!$B$10)^10 | M15: ='Assumptions'!$B$9*(1-'Assumptions'!$B$10)^11
A16: Month 14 | B16: ='Assumptions'!$B$8*(1-'Assumptions'!$B$10)^6 | C16: ='Assumptions'!$B$8*(1-'Assumptions'!$B$10)^12 | D16: ='Assumptions'!$B$8*(1-'Assumptions'!$B$10)^24 | E16: ='Assumptions'!$B$9*(1-'Assumptions'!$B$10)^3 | F16: ='Assumptions'!$B$9*(1-'Assumptions'!$B$10)^4 | G16: ='Assumptions'!$B$9*(1-'Assumptions'!$B$10)^5 | H16: ='Assumptions'!$B$9*(1-'Assumptions'!$B$10)^6 | I16: ='Assumptions'!$B$9*(1-'Assumptions'!$B$10)^7 | J16: ='Assumptions'!$B$9*(1-'Assumptions'!$B$10)^8 | K16: ='Assumptions'!$B$9*(1-'Assumptions'!$B$10)^9 | L16: ='Assumptions'!$B$9*(1-'Assumptions'!$B$10)^10
A17: Month 15 | B17: ='Assumptions'!$B$8*(1-'Assumptions'!$B$10)^6 | C17: ='Assumptions'!$B$8*(1-'Assumptions'!$B$10)^12 | D17: ='Assumptions'!$B$8*(1-'Assumptions'!$B$10)^24 | E17: ='Assumptions'!$B$9*(1-'Assumptions'!$B$10)^3 | F17: ='Assumptions'!$B$9*(1-'Assumptions'!$B$10)^4 | G17: ='Assumptions'!$B$9*(1-'Assumptions'!$B$10)^5 | H17: ='Assumptions'!$B$9*(1-'Assumptions'!$B$10)^6 | I17: ='Assumptions'!$B$9*(1-'Assumptions'!$B$10)^7 | J17: ='Assumptions'!$B$9*(1-'Assumptions'!$B$10)^8 | K17: ='Assumptions'!$B$9*(1-'Assumptions'!$B$10)^9
A18: Month 16 | B18: ='Assumptions'!$B$8*(1-'Assumptions'!$B$10)^6 | C18: ='Assumptions'!$B$8*(1-'Assumptions'!$B$10)^12 | D18: ='Assumptions'!$B$8*(1-'Assumptions'!$B$10)^24 | E18: ='Assumptions'!$B$9*(1-'Assumptions'!$B$10)^3 | F18: ='Assumptions'!$B$9*(1-'Assumptions'!$B$10)^4 | G18: ='Assumptions'!$B$9*(1-'Assumptions'!$B$10)^5 | H18: ='Assumptions'!$B$9*(1-'Assumptions'!$B$10)^6 | I18: ='Assumptions'!$B$9*(1-'Assumptions'!$B$10)^7 | J18: ='Assumptions'!$B$9*(1-'Assumptions'!$B$10)^8
A19: Month 17 | B19: ='Assumptions'!$B$8*(1-'Assumptions'!$B$10)^6 | C19: ='Assumptions'!$B$8*(1-'Assumptions'!$B$10)^12 | D19: ='Assumptions'!$B$8*(1-'Assumptions'!$B$10)^24 | E19: ='Assumptions'!$B$9*(1-'Assumptions'!$B$10)^3 | F19: ='Assumptions'!$B$9*(1-'Assumptions'!$B$10)^4 | G19: ='Assumptions'!$B$9*(1-'Assumptions'!$B$10)^5 | H19: ='Assumptions'!$B$9*(1-'Assumptions'!$B$10)^6 | I19: ='Assumptions'!$B$9*(1-'Assumptions'!$B$10)^7
A20: Month 18 | B20: ='Assumptions'!$B$8*(1-'Assumptions'!$B$10)^6 | C20: ='Assumptions'!$B$8*(1-'Assumptions'!$B$10)^12 | D20: ='Assumptions'!$B$8*(1-'Assumptions'!$B$10)^24 | E20: ='Assumptions'!$B$9*(1-'Assumptions'!$B$10)^3 | F20: ='Assumptions'!$B$9*(1-'Assumptions'!$B$10)^4 | G20: ='Assumptions'!$B$9*(1-'Assumptions'!$B$10)^5 | H20: ='Assumptions'!$B$9*(1-'Assumptions'!$B$10)^6
A21: Month 19 | B21: ='Assumptions'!$B$8*(1-'Assumptions'!$B$10)^6 | C21: ='Assumptions'!$B$8*(1-'Assumptions'!$B$10)^12 | D21: ='Assumptions'!$B$8*(1-'Assumptions'!$B$10)^24 | E21: ='Assumptions'!$B$9*(1-'Assumptions'!$B$10)^3 | F21: ='Assumptions'!$B$9*(1-'Assumptions'!$B$10)^4 | G21: ='Assumptions'!$B$9*(1-'Assumptions'!$B$10)^5
A22: Month 20 | B22: ='Assumptions'!$B$8*(1-'Assumptions'!$B$10)^6 | C22: ='Assumptions'!$B$8*(1-'Assumptions'!$B$10)^12 | D22: ='Assumptions'!$B$8*(1-'Assumptions'!$B$10)^24 | E22: ='Assumptions'!$B$9*(1-'Assumptions'!$B$10)^3 | F22: ='Assumptions'!$B$9*(1-'Assumptions'!$B$10)^4
A23: Month 21 | B23: ='Assumptions'!$B$8*(1-'Assumptions'!$B$10)^6 | C23: ='Assumptions'!$B$8*(1-'Assumptions'!$B$10)^12 | D23: ='Assumptions'!$B$8*(1-'Assumptions'!$B$10)^24 | E23: ='Assumptions'!$B$9*(1-'Assumptions'!$B$10)^3
A24: Month 22 | B24: ='Assumptions'!$B$8*(1-'Assumptions'!$B$10)^6 | C24: ='Assumptions'!$B$8*(1-'Assumptions'!$B$10)^12 | D24: ='Assumptions'!$B$8*(1-'Assumptions'!$B$10)^24
A25: Month 23 | B25: ='Assumptions'!$B$8*(1-'Assumptions'!$B$10)^6 | C25: ='Assumptions'!$B$8*(1-'Assumptions'!$B$10)^12 | D25: ='Assumptions'!$B$8*(1-'Assumptions'!$B$10)^24
A26: Month 24 | B26: ='Assumptions'!$B$8*(1-'Assumptions'!$B$10)^6 | C26: ='Assumptions'!$B$8*(1-'Assumptions'!$B$10)^12 | D26: ='Assumptions'!$B$8*(1-'Assumptions'!$B$10)^24

Sheet KPI_Dashboard
A1: KPI | B1: Unit | C1: Base | D1: Best | E1: Worst
A2: MRR Month 12 (€) | B2: € per month | C2: ='P&L_Monthly'!M7 | D2: ='P&L_Monthly'!M8 | E2: ='P&L_Monthly'!M9
A3: MRR Month 24 (€) | B3: € per month | C3: ='P&L_Monthly'!Y7 | D3: ='P&L_Monthly'!Y8 | E3: ='P&L_Monthly'!Y9
A4: ARR run-rate Month 24 (€) | B4: € per year | C4: =12*'P&L_Monthly'!Y7 | D4: =12*'P&L_Monthly'!Y8 | E4: =12*'P&L_Monthly'!Y9
A5: Avg monthly burn (EBITDA) | B5: € per month | C5: ='Scenarios'!B2 | D5: ='Scenarios'!C2 | E5: ='Scenarios'!D2
A6: Runway (months) | B6: months | C6: ='Scenarios'!B3 | D6: ='Scenarios'!C3 | E6: ='Scenarios'!D3
A7: LTV/CAC | B7: ratio (x) | C7: ='SaaS_Unit_Econ'!B6 | D7: ='SaaS_Unit_Econ'!C6 | E7: ='SaaS_Unit_Econ'!D6
A8: CAC payback (months) | B8: months | C8: ='SaaS_Unit_Econ'!B7 | D8: ='SaaS_Unit_Econ'!C7 | E8: ='SaaS_Unit_Econ'!D7
A9: Median ARR/FTE 24m | B9: € per FTE | C9: ='Headcount_ARR_per_FTE'!B28 | D9: ='Headcount_ARR_per_FTE'!B29 | E9: ='Headcount_ARR_per_FTE'!B30
A10: Rule of 40 | B10: decimal (e.g. 0.45) | C10: ='Rule_of_40'!B6 | D10: ='Rule_of_40'!C6 | E10: ='Rule_of_40'!D6

Sheet Charts
A1: Charts overview

Sheet Charts_KPIs
A1: KPI charts (Runway, LTV/CAC, Rule of 40)

Sheet How_to_Use
A1: How to use this model
A2: 1. Start from the 'Assumptions' sheet: adjust price, churn, growth, salaries, taxes and capex. 2. The 'P&L_Monthly' sheet recalculates monthly customers, revenue, costs, EBITDA and net income. 3. The 'Cash_Runway' sheet shows closing cash per month and runway in months by scenario. 4. 'SaaS_Unit_Econ' computes CAC, LTV, payback and NRR; 'Headcount_ARR_per_FTE' tracks efficiency. 5. 'Rule_of_40' and 'KPI_Dashboard' summarize the main health indicators used by investors. 6. Use 'Charts' and 'Charts_KPIs' for visuals; 'Cohort_Analysis' for retention/cohort patterns. 7. Read this file together with the 1-page PDF and README on GitHub for full context.

Sheet Config
A1: Scenario selection
A2: Type one of: Base, Best, Worst
A4: Selected scenario | B4: Base

Sheet Single_Scenario_View
A1: Metric | B1: Month 1 | C1: Month 2 | D1: Month 3 | E1: Month 4 | F1: Month 5 | G1: Month 6 | H1: Month 7 | I1: Month 8 | J1: Month 9 | K1: Month 10 | L1: Month 11 | M1: Month 12 | N1: Month 13 | O1: Month 14 | P1: Month 15 | Q1: Month 16 | R1: Month 17 | S1: Month 18 | T1: Month 19 | U1: Month 20 | V1: Month 21 | W1: Month 22 | X1: Month 23 | Y1: Month 24
A3: Customers | B3: =CHOOSE(MATCH(Config!$B$4,{"Base","Best","Worst"},0),'P&L_Monthly'!B3,'P&L_Monthly'!B4,'P&L_Monthly'!B5) | C3: =CHOOSE(MATCH(Config!$B$4,{"Base","Best","Worst"},0),'P&L_Monthly'!C3,'P&L_Monthly'!C4,'P&L_Monthly'!C5) | D3: =CHOOSE(MATCH(Config!$B$4,{"Base","Best","Worst"},0),'P&L_Monthly'!D3,'P&L_Monthly'!D4,'P&L_Monthly'!D5) | E3: =CHOOSE(MATCH(Config!$B$4,{"Base","Best","Worst"},0),'P&L_Monthly'!E3,'P&L_Monthly'!E4,'P&L_Monthly'!E5) | F3: =CHOOSE(MATCH(Config!$B$4,{"Base","Best","Worst"},0),'P&L_Monthly'!F3,'P&L_Monthly'!F4,'P&L_Monthly'!F5) | G3: =CHOOSE(MATCH(Config!$B$4,{"Base","Best","Worst"},0),'P&L_Monthly'!G3,'P&L_Monthly'!G4,'P&L_Monthly'!G5) | H3: =CHOOSE(MATCH(Config!$B$4,{"Base","Best","Worst"},0),'P&L_Monthly'!H3,'P&L_Monthly'!H4,'P&L_Monthly'!H5) | I3: =CHOOSE(MATCH(Config!$B$4,{"Base","Best","Worst"},0),'P&L_Monthly'!I3,'P&L_Monthly'!I4,'P&L_Monthly'!I5) | ... Y3: =CHOOSE(MATCH(Config!$B$4,{"Base","Best","Worst"},0),'P&L_Monthly'!Y3,'P&L_Monthly'!Y4,'P&L_Monthly'!Y5)
A4: Revenue (€) | B4: =CHOOSE(MATCH(Config!$B$4,{"Base","Best","Worst"},0),'P&L_Monthly'!B7,'P&L_Monthly'!B8,'P&L_Monthly'!B9) | C4: =CHOOSE(MATCH(Config!$B$4,{"Base","Best","Worst"},0),'P&L_Monthly'!C7,'P&L_Monthly'!C8,'P&L_Monthly'!C9) | D4: =CHOOSE(MATCH(Config!$B$4,{"Base","Best","Worst"},0),'P&L_Monthly'!D7,'P&L_Monthly'!D8,'P&L_Monthly'!D9) | E4: =CHOOSE(MATCH(Config!$B$4,{"Base","Best","Worst"},0),'P&L_Monthly'!E7,'P&L_Monthly'!E8,'P&L_Monthly'!E9) | F4: =CHOOSE(MATCH(Config!$B$4,{"Base","Best","Worst"},0),'P&L_Monthly'!F7,'P&L_Monthly'!F8,'P&L_Monthly'!F9) | G4: =CHOOSE(MATCH(Config!$B$4,{"Base","Best","Worst"},0),'P&L_Monthly'!G7,'P&L_Monthly'!G8,'P&L_Monthly'!G9) | H4: =CHOOSE(MATCH(Config!$B$4,{"Base","Best","Worst"},0),'P&L_Monthly'!H7,'P&L_Monthly'!H8,'P&L_Monthly'!H9) | I4: =CHOOSE(MATCH(Config!$B$4,{"Base","Best","Worst"},0),'P&L_Monthly'!I7,'P&L_Monthly'!I8,'P&L_Monthly'!I9) | ... Y4: =CHOOSE(MATCH(Config!$B$4,{"Base","Best","Worst"},0),'P&L_Monthly'!Y7,'P&L_Monthly'!Y8,'P&L_Monthly'!Y9)
A5: EBITDA (€) | B5: =CHOOSE(MATCH(Config!$B$4,{"Base","Best","Worst"},0),'P&L_Monthly'!B31,'P&L_Monthly'!B32,'P&L_Monthly'!B33) | C5: =CHOOSE(MATCH(Config!$B$4,{"Base","Best","Worst"},0),'P&L_Monthly'!C31,'P&L_Monthly'!C32,'P&L_Monthly'!C33) | D5: =CHOOSE(MATCH(Config!$B$4,{"Base","Best","Worst"},0),'P&L_Monthly'!D31,'P&L_Monthly'!D32,'P&L_Monthly'!D33) | E5: =CHOOSE(MATCH(Config!$B$4,{"Base","Best","Worst"},0),'P&L_Monthly'!E31,'P&L_Monthly'!E32,'P&L_Monthly'!E33) | F5: =CHOOSE(MATCH(Config!$B$4,{"Base","Best","Worst"},0),'P&L_Monthly'!F31,'P&L_Monthly'!F32,'P&L_Monthly'!F33) | G5: =CHOOSE(MATCH(Config!$B$4,{"Base","Best","Worst"},0),'P&L_Monthly'!G31,'P&L_Monthly'!G32,'P&L_Monthly'!G33) | H5: =CHOOSE(MATCH(Config!$B$4,{"Base","Best","Worst"},0),'P&L_Monthly'!H31,'P&L_Monthly'!H32,'P&L_Monthly'!H33) | I5: =CHOOSE(MATCH(Config!$B$4,{"Base","Best","Worst"},0),'P&L_Monthly'!I31,'P&L_Monthly'!I32,'P&L_Monthly'!I33) | ... Y5: =CHOOSE(MATCH(Config!$B$4,{"Base","Best","Worst"},0),'P&L_Monthly'!Y31,'P&L_Monthly'!Y32,'P&L_Monthly'!Y33)
A6: Closing cash (€) | B6: =CHOOSE(MATCH(Config!$B$4,{"Base","Best","Worst"},0),'Cash_Runway'!B5,'Cash_Runway'!B9,'Cash_Runway'!B13) | C6: =CHOOSE(MATCH(Config!$B$4,{"Base","Best","Worst"},0),'Cash_Runway'!C5,'Cash_Runway'!C9,'Cash_Runway'!C13) | D6: =CHOOSE(MATCH(Config!$B$4,{"Base","Best","Worst"},0),'Cash_Runway'!D5,'Cash_Runway'!D9,'Cash_Runway'!D13) | E6: =CHOOSE(MATCH(Config!$B$4,{"Base","Best","Worst"},0),'Cash_Runway'!E5,'Cash_Runway'!E9,'Cash_Runway'!E13) | F6: =CHOOSE(MATCH(Config!$B$4,{"Base","Best","Worst"},0),'Cash_Runway'!F5,'Cash_Runway'!F9,'Cash_Runway'!F13) | G6: =CHOOSE(MATCH(Config!$B$4,{"Base","Best","Worst"},0),'Cash_Runway'!G5,'Cash_Runway'!G9,'Cash_Runway'!G13) | H6: =CHOOSE(MATCH(Config!$B$4,{"Base","Best","Worst"},0),'Cash_Runway'!H5,'Cash_Runway'!H9,'Cash_Runway'!H13) | I6: =CHOOSE(MATCH(Config!$B$4,{"Base","Best","Worst"},0),'Cash_Runway'!I5,'Cash_Runway'!I9,'Cash_Runway'!I13) | ... Y6: =CHOOSE(MATCH(Config!$B$4,{"Base","Best","Worst"},0),'Cash_Runway'!Y5,'Cash_Runway'!Y9,'Cash_Runway'!Y13)

Sheet Yearly_PnL
A1: Metric | B1: Base Year 1 | C1: Base Year 2 | D1: Best Year 1 | E1: Best Year 2 | F1: Worst Year 1 | G1: Worst Year 2
A2: Revenue (€) | B2: =SUM('P&L_Monthly'!B7:M7) | C2: =SUM('P&L_Monthly'!N7:Y7) | D2: =SUM('P&L_Monthly'!B8:M8) | E2: =SUM('P&L_Monthly'!N8:Y8) | F2: =SUM('P&L_Monthly'!B9:M9) | G2: =SUM('P&L_Monthly'!N9:Y9)
A3: Gross margin (€) | B3: =SUM('P&L_Monthly'!B15:M15) | C3: =SUM('P&L_Monthly'!N15:Y15) | D3: =SUM('P&L_Monthly'!B16:M16) | E3: =SUM('P&L_Monthly'!N16:Y16) | F3: =SUM('P&L_Monthly'!B17:M17) | G3: =SUM('P&L_Monthly'!N17:Y17)
A4: EBITDA (€) | B4: =SUM('P&L_Monthly'!B31:M31) | C4: =SUM('P&L_Monthly'!N31:Y31) | D4: =SUM('P&L_Monthly'!B32:M32) | E4: =SUM('P&L_Monthly'!N32:Y32) | F4: =SUM('P&L_Monthly'!B33:M33) | G4: =SUM('P&L_Monthly'!N33:Y33)
A5: Net income (€) | B5: =SUM('P&L_Monthly'!B43:M43) | C5: =SUM('P&L_Monthly'!N43:Y43) | D5: =SUM('P&L_Monthly'!B44:M44) | E5: =SUM('P&L_Monthly'!N44:Y44) | F5: =SUM('P&L_Monthly'!B45:M45) | G5: =SUM('P&L_Monthly'!N45:Y45)
A6: Revenue growth Year2 vs Year1 | B6: =IF(B2>0,C2/B2-1,0) | D6: =IF(D2>0,E2/D2-1,0) | F6: =IF(F2>0,G2/F2-1,0)
A7: EBITDA growth Year2 vs Year1 | B7: =IF(B4>0,C4/B4-1,0) | D7: =IF(D4>0,E4/D4-1,0) | F7: =IF(F4>0,G4/F4-1,0)
